restcodegen/__init__.py
restcodegen/cli/__init__.py
restcodegen/cli/main.py
restcodegen/generator/__init__.py
restcodegen/generator/base.py
restcodegen/generator/log.py
restcodegen/generator/parameters.py
restcodegen/generator/parser.py
restcodegen/generator/rest_codegen.py
restcodegen/generator/spec_loader.py
restcodegen/generator/spec_patcher.py
restcodegen/generator/utils.py
restcodegen/restclient/__init__.py
restcodegen/restclient/client.py
restcodegen/restclient/configuration.py
restcodegen/templates/api_client.jinja2
restcodegen/templates/apis_init.jinja2
restcodegen/templates/header.jinja2
restcodegen-1.1.1.dist-info/LICENSE
restcodegen-1.1.1.dist-info/METADATA
restcodegen-1.1.1.dist-info/WHEEL
restcodegen-1.1.1.dist-info/entry_points.txt
restcodegen-1.1.1.dist-info/RECORD
