Metadata-Version: 2.1
Name: restcodegen
Version: 1.1.1
Summary: 
Author: Menshikov Valeriy Sergeevich
Author-email: valeriy.menshikov.1989@gmail.com
Requires-Python: >=3.10,<4.0
Classifier: Programming Language :: Python :: 3
Classifier: Programming Language :: Python :: 3.10
Classifier: Programming Language :: Python :: 3.11
Classifier: Programming Language :: Python :: 3.12
Classifier: Programming Language :: Python :: 3.13
Requires-Dist: click (>=8.1.8,<10.0.0)
Requires-Dist: curlify2 (>=2.0.0,<3.0.0)
Requires-Dist: datamodel-code-generator (>=0.26.5,<1.0.0)
Requires-Dist: httpx (>=0.28.1,<1.0.0)
Requires-Dist: jinja2 (>=3.1.5,<4.0.0)
Requires-Dist: loguru (>=0.7.3,<1.0.0)
Requires-Dist: pydantic-settings (>=2.7.1,<3.0.0)
Requires-Dist: ruff (>=0.9.2,<1.0.0)
Requires-Dist: structlog (>=25.1.0,<27.0.0)
